GPRas/GPRas.py
GPRas/__init__.py
GPRas/GPRa/GPR_algorithms.py
GPRas/GPRa/__init__.py
GPRas/GPRa/input_func.py
GPRas/GPRa/output_func.py
GPRas/GPRa/input_funcs/DataImport_nx.py
GPRas/GPRa/input_funcs/FileReading_csv.py
GPRas/GPRa/input_funcs/__init__.py
GPRas/GPRa/output_funcs/__init__.py
GPRas/GPRa/output_funcs/to_csv.py
GPRas/GPRa/output_funcs/to_nx.py
GPRas/GPRa/output_funcs/to_shps.py
GPRas-0.1.1.dist-info/DESCRIPTION.rst
GPRas-0.1.1.dist-info/METADATA
GPRas-0.1.1.dist-info/RECORD
GPRas-0.1.1.dist-info/WHEEL
GPRas-0.1.1.dist-info/metadata.json
GPRas-0.1.1.dist-info/top_level.txt
