Metadata-Version: 2.0
Name: GPRas
Version: 0.1.1
Summary: algorithms for measuring concentration distribution in a spatial network.
Home-page: https://bitbucket.org/wcchin/gpras
Author: Benny Chin
Author-email: wcchin.88@gmal.com
License: UNKNOWN
Keywords: spatial network concentration
Platform: UNKNOWN
Classifier: Development Status :: 3 - Alpha
Classifier: Intended Audience :: Science/Research
Classifier: Topic :: Scientific/Engineering :: GIS
Classifier: License :: OSI Approved :: MIT License
Classifier: Programming Language :: Python :: 2.7
Requires-Dist: geopandas
Requires-Dist: networkx
Requires-Dist: numpy
Requires-Dist: pandas
Requires-Dist: shapely
